mcp_mysql_server/__init__.py
mcp_mysql_server/server.py
mcp_mysql_tool-0.2.3.dist-info/licenses/LICENSE
mcp_mysql_tool-0.2.3.dist-info/METADATA
mcp_mysql_tool-0.2.3.dist-info/WHEEL
mcp_mysql_tool-0.2.3.dist-info/entry_points.txt
mcp_mysql_tool-0.2.3.dist-info/top_level.txt
mcp_mysql_tool-0.2.3.dist-info/RECORD
