Metadata-Version: 2.4
Name: mcp-mysql-tool
Version: 0.2.3
Summary: MySQL MCP Server for AI database operations
Author: Mrbeandev
Author-email: Mrbeandev <mrbeandev@gmail.com>
License: MIT
Project-URL: Homepage, https://github.com/mrbeandev
Project-URL: Developers, https://mrbean.dev
Keywords: mysql,mcp,ai,database,model-context-protocol
Classifier: Development Status :: 4 - Beta
Classifier: Intended Audience :: Developers
Classifier: License :: OSI Approved :: MIT License
Classifier: Programming Language :: Python :: 3
Classifier: Programming Language :: Python :: 3.8
Classifier: Programming Language :: Python :: 3.9
Classifier: Programming Language :: Python :: 3.10
Classifier: Programming Language :: Python :: 3.11
Classifier: Programming Language :: Python :: 3.12
Requires-Python: >=3.8
License-File: LICENSE
Requires-Dist: mcp>=1.15.0
Requires-Dist: mysql-connector-python>=9.0.0
Dynamic: author
Dynamic: license-file
Dynamic: requires-python
